odoo/addons/sale_partner_order_template/README.rst
odoo/addons/sale_partner_order_template/__init__.py
odoo/addons/sale_partner_order_template/__manifest__.py
odoo/addons/sale_partner_order_template/i18n/it.po
odoo/addons/sale_partner_order_template/i18n/sale_partner_order_template.pot
odoo/addons/sale_partner_order_template/models/__init__.py
odoo/addons/sale_partner_order_template/models/res_partner.py
odoo/addons/sale_partner_order_template/models/sale_order.py
odoo/addons/sale_partner_order_template/readme/CONTRIBUTORS.md
odoo/addons/sale_partner_order_template/readme/DESCRIPTION.md
odoo/addons/sale_partner_order_template/readme/USAGE.md
odoo/addons/sale_partner_order_template/static/description/icon.png
odoo/addons/sale_partner_order_template/static/description/index.html
odoo/addons/sale_partner_order_template/static/img/readme/ORDER_TEMPLATE.png
odoo/addons/sale_partner_order_template/static/img/readme/PARTNER_ORDER_TEMPLATE.png
odoo/addons/sale_partner_order_template/views/res_partner_views.xml
odoo_addon_sale_partner_order_template-17.0.1.0.0.4.dist-info/METADATA
odoo_addon_sale_partner_order_template-17.0.1.0.0.4.dist-info/WHEEL
odoo_addon_sale_partner_order_template-17.0.1.0.0.4.dist-info/top_level.txt
odoo_addon_sale_partner_order_template-17.0.1.0.0.4.dist-info/RECORD
